genreg/__init__.py
genreg/region.py
genreg/tests/__init__.py
genreg/tests/testregion.py
genreg-1.0.3.dist-info/LICENSE
genreg-1.0.3.dist-info/METADATA
genreg-1.0.3.dist-info/WHEEL
genreg-1.0.3.dist-info/top_level.txt
genreg-1.0.3.dist-info/RECORD
