Metadata-Version: 2.1
Name: genreg
Version: 1.0.3
Summary: Genomic region package for learning purposes
Author-email: András Aszódi <andras.aszodi@vbcf.ac.at>
License: This package is made available under the terms of the MIT license.
Project-URL: Homepage, https://training.vbcf.ac.at/training/pylang.php
Classifier: Programming Language :: Python :: 3
Classifier: License :: OSI Approved :: MIT License
Classifier: Operating System :: OS Independent
Requires-Python: >=3.8
License-File: LICENSE
